ml_ecolyzer-1.1.2.dist-info/licenses/LICENSE
mlecolyzer/__init__.py
mlecolyzer/_version.py
mlecolyzer/cli/__init__.py
mlecolyzer/cli/main.py
mlecolyzer/core/__init__.py
mlecolyzer/core/config.py
mlecolyzer/core/research.py
mlecolyzer/core/runner.py
mlecolyzer/data/gpus.csv
mlecolyzer/data/impact.csv
mlecolyzer/data/instances.csv
mlecolyzer/datasets/__init__.py
mlecolyzer/datasets/loader.py
mlecolyzer/metrics/__init__.py
mlecolyzer/metrics/accuracy.py
mlecolyzer/models/__init__.py
mlecolyzer/models/loader.py
mlecolyzer/monitoring/__init__.py
mlecolyzer/monitoring/environmental.py
mlecolyzer/monitoring/hardware.py
mlecolyzer/utils/__init__.py
mlecolyzer/utils/helpers.py
mlecolyzer/utils/parameters.py
mlecolyzer/utils/validation.py
mlecolyzer/utils/water_utilities.py
ml_ecolyzer-1.1.2.dist-info/METADATA
ml_ecolyzer-1.1.2.dist-info/WHEEL
ml_ecolyzer-1.1.2.dist-info/entry_points.txt
ml_ecolyzer-1.1.2.dist-info/top_level.txt
ml_ecolyzer-1.1.2.dist-info/RECORD
